pydantic2ts/__init__.py
pydantic2ts/cli/__init__.py
pydantic2ts/cli/script.py
pydantic_to_typescript-1.0.10.dist-info/LICENSE.md
pydantic_to_typescript-1.0.10.dist-info/METADATA
pydantic_to_typescript-1.0.10.dist-info/WHEEL
pydantic_to_typescript-1.0.10.dist-info/entry_points.txt
pydantic_to_typescript-1.0.10.dist-info/top_level.txt
pydantic_to_typescript-1.0.10.dist-info/RECORD
