Metadata-Version: 2.1
Name: pydantic-to-typescript
Version: 1.0.10
Summary: Convert pydantic models to typescript interfaces
Home-page: https://github.com/phillipdupuis/pydantic-to-typescript
Author: Phillip Dupuis
Author-email: phillip_dupuis@alumni.brown.edu
License: MIT
Keywords: pydantic typescript annotations validation interface
Platform: UNKNOWN
Classifier: Development Status :: 5 - Production/Stable
Classifier: License :: OSI Approved :: MIT License
Classifier: Programming Language :: Python
Classifier: Programming Language :: Python :: 3
Classifier: Programming Language :: Python :: 3 :: Only
Classifier: Programming Language :: Python :: 3.6
Classifier: Programming Language :: Python :: 3.7
Classifier: Programming Language :: Python :: 3.8
Classifier: Programming Language :: Python :: 3.9
Classifier: Programming Language :: Python :: 3.10
Provides-Extra: dev
